setup.py
rocketreach/__init__.py
rocketreach/account.py
rocketreach/account_gateway.py
rocketreach/exceptions.py
rocketreach/gateway.py
rocketreach/person.py
rocketreach/person_gateway.py
rocketreach/person_search.py
rocketreach/resource.py
rocketreach/result.py
rocketreach/version.py
rocketreach_python.egg-info/PKG-INFO
rocketreach_python.egg-info/SOURCES.txt
rocketreach_python.egg-info/dependency_links.txt
rocketreach_python.egg-info/requires.txt
rocketreach_python.egg-info/top_level.txt