Metadata-Version: 1.2
Name: rocketreach-python
Version: 2.0.1
Summary: Python bindings for RocketReach API
Home-page: https://github.com/punihaol/rocketreach_python
Author: RocketReach
Author-email: engineering@rocketreach.co
License: MIT
Project-URL: Documentation, https://rocketreach.co/api
Project-URL: Source Code, https://github.com/punihaol/rocketreach_python
Platform: UNKNOWN
Requires-Python: >=2.7, !=3.0.*, !=3.1.*, !=3.2.*, !=3.3.*
